[{"place_id": 25178160, "licence": "Data \u00a9 OpenStreetMap contributors, ODbL 1.0. http://osm.org/copyright", "osm_type": "way", "osm_id": 928228540, "lat": "-7.9207887", "lon": "112.5969056", "class": "amenity", "type": "university", "place_rank": 30, "importance": 4.0000762951049326e-05, "addresstype": "amenity", "name": "Universitas Muhammadiyah Malang", "display_name": "Universitas Muhammadiyah Malang, Gang 15B, RW 07, Kel Tlogomas, Kec Lowokwaru, Kota Malang, Tlogomas, Malang, Kota Malang, East Java, Java, 65144, Indonesia", "boundingbox": ["-7.9237747", "-7.9177854", "112.5932497", "112.6023665"]}]